{
  "date": "2025_10_09",
  "videos": [
    {
      "filename": "videos/2025_10_09/2025_10_09_01.mp4",
      "thumb_path": "videos/2025_10_09/2025_10_09_01_thumb.webp",
      "timestamp": "2025-10-09T00:42:07.772904Z"
    },
    {
      "filename": "videos/2025_10_09/2025_10_09_02.mp4",
      "thumb_path": "videos/2025_10_09/2025_10_09_02_thumb.webp",
      "timestamp": "2025-10-09T02:13:44.124104Z"
    },
    {
      "filename": "videos/2025_10_09/2025_10_09_03.mp4",
      "thumb_path": "videos/2025_10_09/2025_10_09_03_thumb.webp",
      "timestamp": "2025-10-09T03:09:00.819118Z"
    },
    {
      "filename": "videos/2025_10_09/2025_10_09_04.mp4",
      "thumb_path": "videos/2025_10_09/2025_10_09_04_thumb.webp",
      "timestamp": "2025-10-09T03:40:05.508926Z"
    },
    {
      "filename": "videos/2025_10_09/2025_10_09_05.mp4",
      "thumb_path": "videos/2025_10_09/2025_10_09_05_thumb.webp",
      "timestamp": "2025-10-09T03:52:55.820865Z"
    },
    {
      "filename": "videos/2025_10_09/2025_10_09_06.mp4",
      "thumb_path": "videos/2025_10_09/2025_10_09_06_thumb.webp",
      "timestamp": "2025-10-09T04:12:28.975667Z"
    },
    {
      "filename": "videos/2025_10_09/2025_10_09_07.mp4",
      "thumb_path": "videos/2025_10_09/2025_10_09_07_thumb.webp",
      "timestamp": "2025-10-09T04:34:43.322975Z"
    },
    {
      "filename": "videos/2025_10_09/2025_10_09_08.mp4",
      "thumb_path": "videos/2025_10_09/2025_10_09_08_thumb.webp",
      "timestamp": "2025-10-09T04:49:53.299492Z"
    },
    {
      "filename": "videos/2025_10_09/2025_10_09_09.mp4",
      "thumb_path": "videos/2025_10_09/2025_10_09_09_thumb.webp",
      "timestamp": "2025-10-09T05:10:58.854641Z"
    },
    {
      "filename": "videos/2025_10_09/2025_10_09_10.mp4",
      "thumb_path": "videos/2025_10_09/2025_10_09_10_thumb.webp",
      "timestamp": "2025-10-09T05:31:39.423296Z"
    },
    {
      "filename": "videos/2025_10_09/2025_10_09_11.mp4",
      "thumb_path": "videos/2025_10_09/2025_10_09_11_thumb.webp",
      "timestamp": "2025-10-09T05:48:29.263046Z"
    },
    {
      "filename": "videos/2025_10_09/2025_10_09_12.mp4",
      "thumb_path": "videos/2025_10_09/2025_10_09_12_thumb.webp",
      "timestamp": "2025-10-09T06:15:39.651675Z"
    },
    {
      "filename": "videos/2025_10_09/2025_10_09_13.mp4",
      "thumb_path": "videos/2025_10_09/2025_10_09_13_thumb.webp",
      "timestamp": "2025-10-09T06:45:43.369058Z"
    },
    {
      "filename": "videos/2025_10_09/2025_10_09_14.mp4",
      "thumb_path": "videos/2025_10_09/2025_10_09_14_thumb.webp",
      "timestamp": "2025-10-09T06:56:11.809841Z"
    },
    {
      "filename": "videos/2025_10_09/2025_10_09_15.mp4",
      "thumb_path": "videos/2025_10_09/2025_10_09_15_thumb.webp",
      "timestamp": "2025-10-09T07:10:51.242044Z"
    },
    {
      "filename": "videos/2025_10_09/2025_10_09_16.mp4",
      "thumb_path": "videos/2025_10_09/2025_10_09_16_thumb.webp",
      "timestamp": "2025-10-09T07:28:52.850374Z"
    },
    {
      "filename": "videos/2025_10_09/2025_10_09_17.mp4",
      "thumb_path": "videos/2025_10_09/2025_10_09_17_thumb.webp",
      "timestamp": "2025-10-09T07:37:34.968086Z"
    }
  ]
}