{
  "items": [
    {
      "id": 73396975,
      "url": "https://image.civitai.com/xG1nkqKTMzGDvpLrqFT7WA/ad5fc53e-8f6f-41cf-891c-da4e260b74b2/original=true/ad5fc53e-8f6f-41cf-891c-da4e260b74b2.jpeg",
      "hash": "UIFrCjbxAC^+_4s;xG%gOFo#xFjFNHxuWUV@",
      "width": 1472,
      "height": 2048,
      "nsfwLevel": "X",
      "type": "image",
      "nsfw": true,
      "browsingLevel": 8,
      "createdAt": "2025-05-01T01:53:01.883Z",
      "postId": 16302593,
      "stats": {
        "cryCount": 143,
        "laughCount": 234,
        "likeCount": 1553,
        "dislikeCount": 0,
        "heartCount": 746,
        "commentCount": 3
      },
      "meta": null,
      "username": "Rodzilla2025X",
      "baseModel": "Pony",
      "modelVersionIds": []
    }
  ],
  "metadata": {
    "nextCursor": "1208|1741116240000",
    "nextPage": "https://civitai.com/api/v1/images?limit=1&nsfw=true&cursor=1208%7C1741116240000"
  }
}