{
  "items": [
    {
      "id": 97722990,
      "url": "https://image.civitai.com/xG1nkqKTMzGDvpLrqFT7WA/8606d032-99e9-46e1-bb26-027a5fa52127/width=1280/8606d032-99e9-46e1-bb26-027a5fa52127.jpeg",
      "hash": "UJGuH^~B0KsmMwj[M_tR0fEM?Hxu%M?Gxut6",
      "width": 1280,
      "height": 1856,
      "nsfwLevel": "X",
      "type": "image",
      "nsfw": true,
      "browsingLevel": 8,
      "createdAt": "2025-09-02T09:17:33.419Z",
      "postId": 21681555,
      "stats": {
        "cryCount": 151,
        "laughCount": 315,
        "likeCount": 2865,
        "dislikeCount": 0,
        "heartCount": 1228,
        "commentCount": 1
      },
      "meta": null,
      "username": "ShishigamiDono",
      "baseModel": "Pony",
      "modelVersionIds": [
        164821,
        382152,
        534756,
        556208,
        596040,
        756152,
        2071650
      ]
    },
    {
      "id": 99560791,
      "url": "https://image.civitai.com/xG1nkqKTMzGDvpLrqFT7WA/30cdba82-9635-4dc8-98b1-dea72bd20ca0/width=1800/30cdba82-9635-4dc8-98b1-dea72bd20ca0.jpeg",
      "hash": "UHHnjZR50~~pm6Ef9Z%2BpVtrWS#^*9ZcF?a",
      "width": 2688,
      "height": 3840,
      "nsfwLevel": "Mature",
      "type": "image",
      "nsfw": true,
      "browsingLevel": 4,
      "createdAt": "2025-09-11T17:57:44.735Z",
      "postId": 22090930,
      "stats": {
        "cryCount": 202,
        "laughCount": 346,
        "likeCount": 2892,
        "dislikeCount": 0,
        "heartCount": 1109,
        "commentCount": 2
      },
      "meta": null,
      "username": "Rodzilla2025X",
      "baseModel": "Illustrious",
      "modelVersionIds": []
    }
  ],
  "metadata": {
    "nextCursor": "233|1757613464735",
    "nextPage": "https://civitai.com/api/v1/images?limit=1&nsfw=true&cursor=233%7C1757613464735"
  }
}