{
  "items": [
    {
      "id": 91162648,
      "url": "https://image.civitai.com/xG1nkqKTMzGDvpLrqFT7WA/9d95e40c-9af7-4519-aa9d-edf86415b380/original=true/9d95e40c-9af7-4519-aa9d-edf86415b380.jpeg",
      "hash": "UFI.,D480$K6~CJ-M{ba0~RQXN,:,[KNni#-",
      "width": 1152,
      "height": 1504,
      "nsfwLevel": "X",
      "type": "image",
      "nsfw": true,
      "browsingLevel": 16,
      "createdAt": "2025-07-29T10:44:53.541Z",
      "postId": 20219439,
      "stats": {
        "cryCount": 301,
        "laughCount": 452,
        "likeCount": 2042,
        "dislikeCount": 0,
        "heartCount": 819,
        "commentCount": 1
      },
      "meta": null,
      "username": "yaoilover004",
      "baseModel": null,
      "modelVersionIds": [
        1777219,
        2054297
      ]
    }
  ],
  "metadata": {
    "nextCursor": "492|1728475953330",
    "nextPage": "https://civitai.com/api/v1/images?limit=1&nsfw=true&cursor=492%7C1728475953330"
  }
}