{
  "items": [
    {
      "id": 70988999,
      "url": "https://image.civitai.com/xG1nkqKTMzGDvpLrqFT7WA/b17158c4-a4b7-4b97-9f15-ae214694a2bf/original=true/b17158c4-a4b7-4b97-9f15-ae214694a2bf.jpeg",
      "hash": "UEIzbdni0g?GM_IV9aE10K?Hxu?G~Voz%MS3",
      "width": 1280,
      "height": 1856,
      "nsfwLevel": "X",
      "type": "image",
      "nsfw": true,
      "browsingLevel": 8,
      "createdAt": "2025-04-20T00:37:00.000Z",
      "postId": 15768431,
      "stats": {
        "cryCount": 103,
        "laughCount": 233,
        "likeCount": 1776,
        "dislikeCount": 0,
        "heartCount": 879,
        "commentCount": 0
      },
      "meta": null,
      "username": "Kalrdr",
      "baseModel": "Illustrious",
      "modelVersionIds": [
        9208,
        111363,
        164821,
        372639,
        1412563,
        1490781,
        1579851
      ]
    }
  ],
  "metadata": {
    "nextCursor": "904|1744776000000",
    "nextPage": "https://civitai.com/api/v1/images?limit=1&nsfw=true&cursor=904%7C1744776000000"
  }
}